yt_cookie_manager/__init__.py
yt_cookie_manager/bot_restarter.py
yt_cookie_manager/cookie_checker.py
yt_cookie_manager/cookie_fetcher.py
yt_cookie_manager/cookie_injector.py
yt_cookie_manager/logger.py
yt_cookie_manager/main.py
yt_cookie_manager/scheduler.py
yt_cookie_manager-0.1.0.dist-info/METADATA
yt_cookie_manager-0.1.0.dist-info/WHEEL
yt_cookie_manager-0.1.0.dist-info/top_level.txt
yt_cookie_manager-0.1.0.dist-info/RECORD
