Metadata-Version: 2.4
Name: yt-cookie-manager
Version: 0.1.0
Summary: YouTube Cookie Manager for Telegram Music Bots
Home-page: https://github.com/kidoocoder/ytdlp
Author: kidoocoder
Author-email: your.email@example.com
Classifier: Programming Language :: Python :: 3
Classifier: License :: OSI Approved :: MIT License
Classifier: Operating System :: OS Independent
Requires-Python: >=3.7
Requires-Dist: selenium>=4.1.0
Requires-Dist: browser-cookie3>=0.19.1
Requires-Dist: requests>=2.28.0
Requires-Dist: pyrogram>=2.0.0
Requires-Dist: schedule>=1.1.0
Requires-Dist: psutil>=5.9.0
Dynamic: author
Dynamic: author-email
Dynamic: classifier
Dynamic: description
Dynamic: description-content-type
Dynamic: home-page
Dynamic: requires-dist
Dynamic: requires-python
Dynamic: summary
